requests_defaults/__init__.py
requests_defaults-0.0.3.dist-info/WHEEL
requests_defaults-0.0.3.dist-info/METADATA
requests_defaults-0.0.3.dist-info/RECORD
