Metadata-Version: 2.1
Name: requests-defaults
Version: 0.0.3
Summary: 
Author: Dani Hodovic
Author-email: dani.hodovic@gmail.com
Requires-Python: >=3.8,<4.0
Classifier: Programming Language :: Python :: 3
Classifier: Programming Language :: Python :: 3.8
Classifier: Programming Language :: Python :: 3.9
Requires-Dist: pytest-cov (>=2.12.1,<3.0.0)
Requires-Dist: pytest-httpserver (>=1.0.1,<2.0.0)
Requires-Dist: pytest-mock (>=3.6.1,<4.0.0)
Requires-Dist: requests-toolbelt (>=0.9.1,<0.10.0)
